{"nhits": 43, "parameters": {"dataset": ["arome-0025-sp1_sp2"], "timezone": "UTC", "rows": 200, "format": "json", "geofilter.distance": ["43.8,4.5,10"]}, "records": [{"datasetid": "arome-0025-sp1_sp2", "recordid": "arome_0025_sp1_sp2_sp3_lastgrib2-1258070", "fields": {"minimum_temperature_at_2_metres_in_the_last_6_hours": 10.56751403808596, "surface_net_thermal_radiation": -703308.125, "2_metre_temperature": 18.767572021484398, "dist": "0", "downward_short_wave_radiation_flux": 4103195.576171875, "surface_net_solar_radiation": 3283072.0, "timestamp": "2019-03-10T12:00:00+00:00", "surface_latent_heat_flux": -779362.0, "surface_sensible_heat_flux": -1314176.0, "total_water_precipitation": 0.0, "relative_humidity": 45.35917663574219, "maximum_temperature_at_2_metres_in_the_last_6_hours": 12.59937438964846, "wind_speed": 12.025803469121456, "position": [43.8, 4.5], "forecast": "2019-03-10T14:00:00+00:00"}, "geometry": {"type": "Point", "coordinates": [4.5, 43.8]}, "record_timestamp": "2019-03-10T12:00:00+00:00"}, {"datasetid": "arome-0025-sp1_sp2", "recordid": "arome_0025_sp1_sp2_sp3_lastgrib2-2702273", "fields": {"surface_net_thermal_radiation": -4492273.5, "wind_speed": 12.35155214369297, "2_metre_temperature": 10.183343505859398, "dist": "0", "downward_short_wave_radiation_flux": 7215691.8671875, "surface_net_solar_radiation": 5771520.0, "timestamp": "2019-03-10T12:00:00+00:00", "surface_latent_heat_flux": -1622990.0, "total_water_precipitation": 0.0, "relative_humidity": 46.77204418182373, "surface_sensible_heat_flux": -321584.0, "position": [43.8, 4.5], "forecast": "2019-03-11T03:00:00+00:00"}, "geometry": {"type": "Point", "coordinates": [4.5, 43.8]}, "record_timestamp": "2019-03-10T12:00:00+00:00"}, {"datasetid": "arome-0025-sp1_sp2", "recordid": "arome_0025_sp1_sp2_sp3_lastgrib2-2220872", "fields": {"surface_net_thermal_radiation": -6663744.0, "wind_speed": 11.469632975757122, "2_metre_temperature": 10.63147888183596, "dist": "0", "downward_short_wave_radiation_flux": 9652559.96875, "surface_net_solar_radiation": 7709696.0, "timestamp": "2019-03-10T12:00:00+00:00", "surface_latent_heat_flux": -2202240.0, "total_water_precipitation": 0.0, "relative_humidity": 42.023152351379395, "surface_sensible_heat_flux": 75304.0, "position": [43.8, 4.5], "forecast": "2019-03-11T09:00:00+00:00"}, "geometry": {"type": "Point", "coordinates": [4.5, 43.8]}, "record_timestamp": "2019-03-10T12:00:00+00:00"}, {"datasetid": "arome-0025-sp1_sp2", "recordid": "arome_0025_sp1_sp2_sp3_lastgrib2-6072080", "fields": {"surface_net_thermal_radiation": -1396807.25, "wind_speed": 10.49838511645794, "2_metre_temperature": 18.161706542968773, "dist": "0", "downward_short_wave_radiation_flux": 6762993.265625, "surface_net_solar_radiation": 5409280.0, "timestamp": "2019-03-10T12:00:00+00:00", "surface_latent_heat_flux": -1274821.0, "total_water_precipitation": 0.0, "relative_humidity": 52.172563552856445, "surface_sensible_heat_flux": -2145094.0, "position": [43.8, 4.5], "forecast": "2019-03-10T16:00:00+00:00"}, "geometry": {"type": "Point", "coordinates": [4.5, 43.8]}, "record_timestamp": "2019-03-10T12:00:00+00:00"}, {"datasetid": "arome-0025-sp1_sp2", "recordid": "arome_0025_sp1_sp2_sp3_lastgrib2-12330293", "fields": {"minimum_temperature_at_2_metres_in_the_last_6_hours": 10.879205322265648, "surface_net_thermal_radiation": -317948.0, "2_metre_temperature": 18.593499755859398, "dist": "0", "downward_short_wave_radiation_flux": 2045701.068359375, "surface_net_solar_radiation": 1636864.0, "timestamp": "2019-03-10T12:00:00+00:00", "surface_latent_heat_flux": -408123.25, "surface_sensible_heat_flux": -579910.25, "total_water_precipitation": 0.0, "relative_humidity": 49.275718688964844, "maximum_temperature_at_2_metres_in_the_last_6_hours": 12.566918945312523, "wind_speed": 9.907299168407917, "position": [43.8, 4.5], "forecast": "2019-03-10T13:00:00+00:00"}, "geometry": {"type": "Point", "coordinates": [4.5, 43.8]}, "record_timestamp": "2019-03-10T12:00:00+00:00"}, {"datasetid": "arome-0025-sp1_sp2", "recordid": "arome_0025_sp1_sp2_sp3_lastgrib2-16181501", "fields": {"surface_net_thermal_radiation": -12666864.0, "wind_speed": 9.734744403511286, "2_metre_temperature": 7.309655761718773, "dist": "0", "downward_short_wave_radiation_flux": 25172507.125, "surface_net_solar_radiation": 20091274.0625, "timestamp": "2019-03-10T12:00:00+00:00", "surface_latent_heat_flux": -4548656.0, "total_water_precipitation": 0.0, "relative_humidity": 47.30955791473389, "surface_sensible_heat_flux": -5357946.0, "position": [43.8, 4.5], "forecast": "2019-03-12T00:00:00+00:00"}, "geometry": {"type": "Point", "coordinates": [4.5, 43.8]}, "record_timestamp": "2019-03-10T12:00:00+00:00"}, {"datasetid": "arome-0025-sp1_sp2", "recordid": "arome_0025_sp1_sp2_sp3_lastgrib2-17144303", "fields": {"surface_net_thermal_radiation": -10253972.0, "wind_speed": 15.719549059867859, "2_metre_temperature": 10.571817016601585, "dist": "0", "downward_short_wave_radiation_flux": 25080878.75, "surface_net_solar_radiation": 20017663.6875, "timestamp": "2019-03-10T12:00:00+00:00", "surface_latent_heat_flux": -4500020.0, "total_water_precipitation": 0.0, "relative_humidity": 45.13619041442871, "surface_sensible_heat_flux": -6336994.0, "position": [43.8, 4.5], "forecast": "2019-03-11T17:00:00+00:00"}, "geometry": {"type": "Point", "coordinates": [4.5, 43.8]}, "record_timestamp": "2019-03-10T12:00:00+00:00"}, {"datasetid": "arome-0025-sp1_sp2", "recordid": "arome_0025_sp1_sp2_sp3_lastgrib2-18107105", "fields": {"surface_net_thermal_radiation": -7555907.0, "wind_speed": 13.12064585275948, "2_metre_temperature": 13.231439208984398, "dist": "0", "downward_short_wave_radiation_flux": 14013694.125, "surface_net_solar_radiation": 11188365.27734375, "timestamp": "2019-03-10T12:00:00+00:00", "surface_latent_heat_flux": -2849996.0, "total_water_precipitation": 0.0, "relative_humidity": 33.042686462402344, "surface_sensible_heat_flux": -1411441.0, "position": [43.8, 4.5], "forecast": "2019-03-11T11:00:00+00:00"}, "geometry": {"type": "Point", "coordinates": [4.5, 43.8]}, "record_timestamp": "2019-03-10T12:00:00+00:00"}, {"datasetid": "arome-0025-sp1_sp2", "recordid": "arome_0025_sp1_sp2_sp3_lastgrib2-20032709", "fields": {"surface_net_thermal_radiation": -2951955.0, "wind_speed": 13.681508863344789, "2_metre_temperature": 13.608605957031273, "dist": "0", "downward_short_wave_radiation_flux": 7215691.8671875, "surface_net_solar_radiation": 5771520.0, "timestamp": "2019-03-10T12:00:00+00:00", "surface_latent_heat_flux": -1462485.0, "total_water_precipitation": 0.0, "relative_humidity": 50.13426208496094, "surface_sensible_heat_flux": -1237745.0, "position": [43.8, 4.5], "forecast": "2019-03-10T22:00:00+00:00"}, "geometry": {"type": "Point", "coordinates": [4.5, 43.8]}, "record_timestamp": "2019-03-10T12:00:00+00:00"}, {"datasetid": "arome-0025-sp1_sp2", "recordid": "arome_0025_sp1_sp2_sp3_lastgrib2-3183674", "fields": {"surface_net_thermal_radiation": -11333484.0, "wind_speed": 11.666766604408622, "2_metre_temperature": 8.356286621093773, "dist": "0", "downward_short_wave_radiation_flux": 25172507.125, "surface_net_solar_radiation": 20091274.0625, "timestamp": "2019-03-10T12:00:00+00:00", "surface_latent_heat_flux": -4539072.0, "total_water_precipitation": 0.0, "relative_humidity": 51.433838844299316, "surface_sensible_heat_flux": -5907110.0, "position": [43.8, 4.5], "forecast": "2019-03-11T20:00:00+00:00"}, "geometry": {"type": "Point", "coordinates": [4.5, 43.8]}, "record_timestamp": "2019-03-10T12:00:00+00:00"}, {"datasetid": "arome-0025-sp1_sp2", "recordid": "arome_0025_sp1_sp2_sp3_lastgrib2-6553481", "fields": {"surface_net_thermal_radiation": -2695961.5, "wind_speed": 14.545775421895087, "2_metre_temperature": 14.272424316406273, "dist": "0", "downward_short_wave_radiation_flux": 7215691.8671875, "surface_net_solar_radiation": 5771520.0, "timestamp": "2019-03-10T12:00:00+00:00", "surface_latent_heat_flux": -1455822.0, "total_water_precipitation": 0.0, "relative_humidity": 59.06930732727051, "surface_sensible_heat_flux": -1432207.5, "position": [43.8, 4.5], "forecast": "2019-03-10T21:00:00+00:00"}, "geometry": {"type": "Point", "coordinates": [4.5, 43.8]}, "record_timestamp": "2019-03-10T12:00:00+00:00"}, {"datasetid": "arome-0025-sp1_sp2", "recordid": "arome_0025_sp1_sp2_sp3_lastgrib2-5109278", "fields": {"surface_net_thermal_radiation": -8031451.0, "wind_speed": 13.736571617424488, "2_metre_temperature": 13.95624694824221, "dist": "0", "downward_short_wave_radiation_flux": 16567731.625, "surface_net_solar_radiation": 13227917.59375, "timestamp": "2019-03-10T12:00:00+00:00", "surface_latent_heat_flux": -3233688.0, "total_water_precipitation": 0.0, "relative_humidity": 29.50996494293213, "surface_sensible_heat_flux": -2425267.0, "position": [43.8, 4.5], "forecast": "2019-03-11T12:00:00+00:00"}, "geometry": {"type": "Point", "coordinates": [4.5, 43.8]}, "record_timestamp": "2019-03-10T12:00:00+00:00"}, {"datasetid": "arome-0025-sp1_sp2", "recordid": "arome_0025_sp1_sp2_sp3_lastgrib2-11367491", "fields": {"surface_net_thermal_radiation": -8510659.0, "wind_speed": 14.411053948104382, "2_metre_temperature": 14.412530517578148, "dist": "0", "downward_short_wave_radiation_flux": 19080868.75, "surface_net_solar_radiation": 15233801.109375, "timestamp": "2019-03-10T12:00:00+00:00", "surface_latent_heat_flux": -3599532.0, "total_water_precipitation": 0.0, "relative_humidity": 27.566099166870117, "surface_sensible_heat_flux": -3476365.0, "position": [43.8, 4.5], "forecast": "2019-03-11T13:00:00+00:00"}, "geometry": {"type": "Point", "coordinates": [4.5, 43.8]}, "record_timestamp": "2019-03-10T12:00:00+00:00"}, {"datasetid": "arome-0025-sp1_sp2", "recordid": "arome_0025_sp1_sp2_sp3_lastgrib2-10404689", "fields": {"surface_net_thermal_radiation": -9444296.0, "wind_speed": 18.69219981878996, "2_metre_temperature": 13.60749206542971, "dist": "0", "downward_short_wave_radiation_flux": 23195882.0, "surface_net_solar_radiation": 18516485.4375, "timestamp": "2019-03-10T12:00:00+00:00", "surface_latent_heat_flux": -4234456.0, "total_water_precipitation": 0.0, "relative_humidity": 33.10060262680054, "surface_sensible_heat_flux": -5261560.0, "position": [43.8, 4.5], "forecast": "2019-03-11T15:00:00+00:00"}, "geometry": {"type": "Point", "coordinates": [4.5, 43.8]}, "record_timestamp": "2019-03-10T12:00:00+00:00"}, {"datasetid": "arome-0025-sp1_sp2", "recordid": "arome_0025_sp1_sp2_sp3_lastgrib2-10886090", "fields": {"surface_net_thermal_radiation": -4172367.0, "wind_speed": 13.430318736471236, "2_metre_temperature": 10.776345825195335, "dist": "0", "downward_short_wave_radiation_flux": 7215691.8671875, "surface_net_solar_radiation": 5771520.0, "timestamp": "2019-03-10T12:00:00+00:00", "surface_latent_heat_flux": -1569296.0, "total_water_precipitation": 0.0, "relative_humidity": 49.09249687194824, "surface_sensible_heat_flux": -520691.5, "position": [43.8, 4.5], "forecast": "2019-03-11T02:00:00+00:00"}, "geometry": {"type": "Point", "coordinates": [4.5, 43.8]}, "record_timestamp": "2019-03-10T12:00:00+00:00"}, {"datasetid": "arome-0025-sp1_sp2", "recordid": "arome_0025_sp1_sp2_sp3_lastgrib2-13293095", "fields": {"surface_net_thermal_radiation": -14432634.0, "wind_speed": 3.927879557479173, "2_metre_temperature": 4.418237304687523, "dist": "0", "downward_short_wave_radiation_flux": 25172507.125, "surface_net_solar_radiation": 20091274.0625, "timestamp": "2019-03-10T12:00:00+00:00", "surface_latent_heat_flux": -4558248.0, "total_water_precipitation": 0.0, "relative_humidity": 51.990675926208496, "surface_sensible_heat_flux": -4786724.0, "position": [43.8, 4.5], "forecast": "2019-03-12T05:00:00+00:00"}, "geometry": {"type": "Point", "coordinates": [4.5, 43.8]}, "record_timestamp": "2019-03-10T12:00:00+00:00"}, {"datasetid": "arome-0025-sp1_sp2", "recordid": "arome_0025_sp1_sp2_sp3_lastgrib2-15700100", "fields": {"surface_net_thermal_radiation": -10981146.0, "wind_speed": 16.477753936313093, "2_metre_temperature": 9.737756347656273, "dist": "0", "downward_short_wave_radiation_flux": 25172507.125, "surface_net_solar_radiation": 20091274.0625, "timestamp": "2019-03-10T12:00:00+00:00", "surface_latent_heat_flux": -4535640.0, "total_water_precipitation": 0.0, "relative_humidity": 38.46972465515137, "surface_sensible_heat_flux": -6014060.0, "position": [43.8, 4.5], "forecast": "2019-03-11T19:00:00+00:00"}, "geometry": {"type": "Point", "coordinates": [4.5, 43.8]}, "record_timestamp": "2019-03-10T12:00:00+00:00"}, {"datasetid": "arome-0025-sp1_sp2", "recordid": "arome_0025_sp1_sp2_sp3_lastgrib2-17625704", "fields": {"surface_net_thermal_radiation": -3537448.0, "wind_speed": 12.471998240565881, "2_metre_temperature": 11.857110595703148, "dist": "0", "downward_short_wave_radiation_flux": 7215691.8671875, "surface_net_solar_radiation": 5771520.0, "timestamp": "2019-03-10T12:00:00+00:00", "surface_latent_heat_flux": -1512818.0, "total_water_precipitation": 0.0, "relative_humidity": 47.044596672058105, "surface_sensible_heat_flux": -916812.5, "position": [43.8, 4.5], "forecast": "2019-03-11T00:00:00+00:00"}, "geometry": {"type": "Point", "coordinates": [4.5, 43.8]}, "record_timestamp": "2019-03-10T12:00:00+00:00"}, {"datasetid": "arome-0025-sp1_sp2", "recordid": "arome_0025_sp1_sp2_sp3_lastgrib2-14255897", "fields": {"minimum_temperature_at_2_metres_in_the_last_6_hours": 10.405801391601585, "surface_net_thermal_radiation": -1069628.0, "2_metre_temperature": 18.830133056640648, "dist": "0", "downward_short_wave_radiation_flux": 5724736.20703125, "surface_net_solar_radiation": 4579712.0, "timestamp": "2019-03-10T12:00:00+00:00", "surface_latent_heat_flux": -1051458.5, "surface_sensible_heat_flux": -1824012.5, "total_water_precipitation": 0.0, "relative_humidity": 46.492929458618164, "maximum_temperature_at_2_metres_in_the_last_6_hours": 12.547036743164085, "wind_speed": 11.870937258005142, "position": [43.8, 4.5], "forecast": "2019-03-10T15:00:00+00:00"}, "geometry": {"type": "Point", "coordinates": [4.5, 43.8]}, "record_timestamp": "2019-03-10T12:00:00+00:00"}, {"datasetid": "arome-0025-sp1_sp2", "recordid": "arome_0025_sp1_sp2_sp3_lastgrib2-14737298", "fields": {"surface_net_thermal_radiation": -2450732.0, "wind_speed": 14.67771247960627, "2_metre_temperature": 14.645623779296898, "dist": "0", "downward_short_wave_radiation_flux": 7215691.8671875, "surface_net_solar_radiation": 5771520.0, "timestamp": "2019-03-10T12:00:00+00:00", "surface_latent_heat_flux": -1452888.0, "total_water_precipitation": 0.0, "relative_humidity": 58.80294990539551, "surface_sensible_heat_flux": -1646677.0, "position": [43.8, 4.5], "forecast": "2019-03-10T20:00:00+00:00"}, "geometry": {"type": "Point", "coordinates": [4.5, 43.8]}, "record_timestamp": "2019-03-10T12:00:00+00:00"}, {"datasetid": "arome-0025-sp1_sp2", "recordid": "arome_0025_sp1_sp2_sp3_lastgrib2-5590679", "fields": {"surface_net_thermal_radiation": -12327528.0, "wind_speed": 8.926844643894583, "2_metre_temperature": 7.481805419921898, "dist": "0", "downward_short_wave_radiation_flux": 25172507.125, "surface_net_solar_radiation": 20091274.0625, "timestamp": "2019-03-10T12:00:00+00:00", "surface_latent_heat_flux": -4546312.0, "total_water_precipitation": 0.0, "relative_humidity": 51.09505271911621, "surface_sensible_heat_flux": -5526450.0, "position": [43.8, 4.5], "forecast": "2019-03-11T23:00:00+00:00"}, "geometry": {"type": "Point", "coordinates": [4.5, 43.8]}, "record_timestamp": "2019-03-10T12:00:00+00:00"}, {"datasetid": "arome-0025-sp1_sp2", "recordid": "arome_0025_sp1_sp2_sp3_lastgrib2-8960486", "fields": {"surface_net_thermal_radiation": -7099731.0, "wind_speed": 12.033629141747952, "2_metre_temperature": 12.011682128906273, "dist": "0", "downward_short_wave_radiation_flux": 11644370.34375, "surface_net_solar_radiation": 9297408.0, "timestamp": "2019-03-10T12:00:00+00:00", "surface_latent_heat_flux": -2496268.0, "total_water_precipitation": 0.0, "relative_humidity": 38.54890727996826, "surface_sensible_heat_flux": -556701.0, "position": [43.8, 4.5], "forecast": "2019-03-11T10:00:00+00:00"}, "geometry": {"type": "Point", "coordinates": [4.5, 43.8]}, "record_timestamp": "2019-03-10T12:00:00+00:00"}, {"datasetid": "arome-0025-sp1_sp2", "recordid": "arome_0025_sp1_sp2_sp3_lastgrib2-11848892", "fields": {"surface_net_thermal_radiation": -5880965.0, "wind_speed": 11.57536443695426, "2_metre_temperature": 8.67389831542971, "dist": "0", "downward_short_wave_radiation_flux": 7406646.9375, "surface_net_solar_radiation": 5923072.0, "timestamp": "2019-03-10T12:00:00+00:00", "surface_latent_heat_flux": -1774614.0, "total_water_precipitation": 0.0, "relative_humidity": 47.66528129577637, "surface_sensible_heat_flux": 389821.0, "position": [43.8, 4.5], "forecast": "2019-03-11T07:00:00+00:00"}, "geometry": {"type": "Point", "coordinates": [4.5, 43.8]}, "record_timestamp": "2019-03-10T12:00:00+00:00"}, {"datasetid": "arome-0025-sp1_sp2", "recordid": "arome_0025_sp1_sp2_sp3_lastgrib2-9441887", "fields": {"surface_net_thermal_radiation": -11667337.0, "wind_speed": 7.362866076873615, "2_metre_temperature": 7.828515625000023, "dist": "0", "downward_short_wave_radiation_flux": 25172507.125, "surface_net_solar_radiation": 20091274.0625, "timestamp": "2019-03-10T12:00:00+00:00", "surface_latent_heat_flux": -4541120.0, "total_water_precipitation": 0.0, "relative_humidity": 53.18367576599121, "surface_sensible_heat_flux": -5834476.0, "position": [43.8, 4.5], "forecast": "2019-03-11T21:00:00+00:00"}, "geometry": {"type": "Point", "coordinates": [4.5, 43.8]}, "record_timestamp": "2019-03-10T12:00:00+00:00"}, {"datasetid": "arome-0025-sp1_sp2", "recordid": "arome_0025_sp1_sp2_sp3_lastgrib2-13774496", "fields": {"surface_net_thermal_radiation": -1657631.0, "wind_speed": 15.718138217926025, "2_metre_temperature": 17.145532226562523, "dist": "0", "downward_short_wave_radiation_flux": 7160257.046875, "surface_net_solar_radiation": 5727232.0, "timestamp": "2019-03-10T12:00:00+00:00", "surface_latent_heat_flux": -1412047.0, "total_water_precipitation": 0.0, "relative_humidity": 53.705209732055664, "surface_sensible_heat_flux": -2191135.5, "position": [43.8, 4.5], "forecast": "2019-03-10T17:00:00+00:00"}, "geometry": {"type": "Point", "coordinates": [4.5, 43.8]}, "record_timestamp": "2019-03-10T12:00:00+00:00"}, {"datasetid": "arome-0025-sp1_sp2", "recordid": "arome_0025_sp1_sp2_sp3_lastgrib2-9923288", "fields": {"surface_net_thermal_radiation": -4830088.5, "wind_speed": 12.46021160716191, "2_metre_temperature": 9.518731689453148, "dist": "0", "downward_short_wave_radiation_flux": 7215691.8671875, "surface_net_solar_radiation": 5771520.0, "timestamp": "2019-03-10T12:00:00+00:00", "surface_latent_heat_flux": -1668910.0, "total_water_precipitation": 0.0, "relative_humidity": 47.02941036224365, "surface_sensible_heat_flux": -126130.0, "position": [43.8, 4.5], "forecast": "2019-03-11T04:00:00+00:00"}, "geometry": {"type": "Point", "coordinates": [4.5, 43.8]}, "record_timestamp": "2019-03-10T12:00:00+00:00"}, {"datasetid": "arome-0025-sp1_sp2", "recordid": "arome_0025_sp1_sp2_sp3_lastgrib2-7997684", "fields": {"surface_net_thermal_radiation": -9868821.0, "wind_speed": 17.263333201408386, "2_metre_temperature": 10.87348327636721, "dist": "0", "downward_short_wave_radiation_flux": 24460091.25, "surface_net_solar_radiation": 19524136.9375, "timestamp": "2019-03-10T12:00:00+00:00", "surface_latent_heat_flux": -4394356.0, "total_water_precipitation": 0.0, "relative_humidity": 42.768067836761475, "surface_sensible_heat_flux": -6083138.0, "position": [43.8, 4.5], "forecast": "2019-03-11T16:00:00+00:00"}, "geometry": {"type": "Point", "coordinates": [4.5, 43.8]}, "record_timestamp": "2019-03-10T12:00:00+00:00"}, {"datasetid": "arome-0025-sp1_sp2", "recordid": "arome_0025_sp1_sp2_sp3_lastgrib2-15218699", "fields": {"surface_net_thermal_radiation": -6254262.0, "wind_speed": 11.283545952290297, "2_metre_temperature": 9.535073852539085, "dist": "0", "downward_short_wave_radiation_flux": 8203308.109375, "surface_net_solar_radiation": 6556160.0, "timestamp": "2019-03-10T12:00:00+00:00", "surface_latent_heat_flux": -1949736.0, "total_water_precipitation": 0.0, "relative_humidity": 45.17039489746094, "surface_sensible_heat_flux": 383263.0, "position": [43.8, 4.5], "forecast": "2019-03-11T08:00:00+00:00"}, "geometry": {"type": "Point", "coordinates": [4.5, 43.8]}, "record_timestamp": "2019-03-10T12:00:00+00:00"}, {"datasetid": "arome-0025-sp1_sp2", "recordid": "arome_0025_sp1_sp2_sp3_lastgrib2-776669", "fields": {"surface_net_thermal_radiation": -14090264.0, "wind_speed": 5.9253558944910765, "2_metre_temperature": 5.230493164062523, "dist": "0", "downward_short_wave_radiation_flux": 25172507.125, "surface_net_solar_radiation": 20091274.0625, "timestamp": "2019-03-10T12:00:00+00:00", "surface_latent_heat_flux": -4556320.0, "total_water_precipitation": 0.0, "relative_humidity": 45.1192045211792, "surface_sensible_heat_flux": -4836238.0, "position": [43.8, 4.5], "forecast": "2019-03-12T04:00:00+00:00"}, "geometry": {"type": "Point", "coordinates": [4.5, 43.8]}, "record_timestamp": "2019-03-10T12:00:00+00:00"}, {"datasetid": "arome-0025-sp1_sp2", "recordid": "arome_0025_sp1_sp2_sp3_lastgrib2-4627877", "fields": {"surface_net_thermal_radiation": -10619193.0, "wind_speed": 16.614614702761173, "2_metre_temperature": 10.411859130859398, "dist": "0", "downward_short_wave_radiation_flux": 25172507.125, "surface_net_solar_radiation": 20091274.0625, "timestamp": "2019-03-10T12:00:00+00:00", "surface_latent_heat_flux": -4531344.0, "total_water_precipitation": 0.0, "relative_humidity": 32.51154327392578, "surface_sensible_heat_flux": -6202984.0, "position": [43.8, 4.5], "forecast": "2019-03-11T18:00:00+00:00"}, "geometry": {"type": "Point", "coordinates": [4.5, 43.8]}, "record_timestamp": "2019-03-10T12:00:00+00:00"}, {"datasetid": "arome-0025-sp1_sp2", "recordid": "arome_0025_sp1_sp2_sp3_lastgrib2-8479085", "fields": {"surface_net_thermal_radiation": -13375078.0, "wind_speed": 10.300260019255802, "2_metre_temperature": 6.60407409667971, "dist": "0", "downward_short_wave_radiation_flux": 25172507.125, "surface_net_solar_radiation": 20091274.0625, "timestamp": "2019-03-10T12:00:00+00:00", "surface_latent_heat_flux": -4552984.0, "total_water_precipitation": 0.0, "relative_humidity": 47.13235664367676, "surface_sensible_heat_flux": -5026940.0, "position": [43.8, 4.5], "forecast": "2019-03-12T02:00:00+00:00"}, "geometry": {"type": "Point", "coordinates": [4.5, 43.8]}, "record_timestamp": "2019-03-10T12:00:00+00:00"}, {"datasetid": "arome-0025-sp1_sp2", "recordid": "arome_0025_sp1_sp2_sp3_lastgrib2-18588506", "fields": {"surface_net_thermal_radiation": -5181782.5, "wind_speed": 11.969523852691054, "2_metre_temperature": 8.878228759765648, "dist": "0", "downward_short_wave_radiation_flux": 7215691.8671875, "surface_net_solar_radiation": 5771520.0, "timestamp": "2019-03-10T12:00:00+00:00", "surface_latent_heat_flux": -1685534.0, "total_water_precipitation": 0.0, "relative_humidity": 48.07197856903076, "surface_sensible_heat_flux": 27481.5, "position": [43.8, 4.5], "forecast": "2019-03-11T05:00:00+00:00"}, "geometry": {"type": "Point", "coordinates": [4.5, 43.8]}, "record_timestamp": "2019-03-10T12:00:00+00:00"}, {"datasetid": "arome-0025-sp1_sp2", "recordid": "arome_0025_sp1_sp2_sp3_lastgrib2-19069907", "fields": {"surface_net_thermal_radiation": -2193437.0, "wind_speed": 14.737829368561506, "2_metre_temperature": 15.058526611328148, "dist": "0", "downward_short_wave_radiation_flux": 7215691.8671875, "surface_net_solar_radiation": 5771520.0, "timestamp": "2019-03-10T12:00:00+00:00", "surface_latent_heat_flux": -1449429.0, "total_water_precipitation": 0.0, "relative_humidity": 52.037139892578125, "surface_sensible_heat_flux": -1868310.0, "position": [43.8, 4.5], "forecast": "2019-03-10T19:00:00+00:00"}, "geometry": {"type": "Point", "coordinates": [4.5, 43.8]}, "record_timestamp": "2019-03-10T12:00:00+00:00"}, {"datasetid": "arome-0025-sp1_sp2", "recordid": "arome_0025_sp1_sp2_sp3_lastgrib2-7034882", "fields": {"surface_net_thermal_radiation": -1913331.5, "wind_speed": 15.668373700231314, "2_metre_temperature": 15.872277832031273, "dist": "0", "downward_short_wave_radiation_flux": 7215691.8671875, "surface_net_solar_radiation": 5771520.0, "timestamp": "2019-03-10T12:00:00+00:00", "surface_latent_heat_flux": -1445541.0, "total_water_precipitation": 0.0, "relative_humidity": 54.54599952697754, "surface_sensible_heat_flux": -2071258.0, "position": [43.8, 4.5], "forecast": "2019-03-10T18:00:00+00:00"}, "geometry": {"type": "Point", "coordinates": [4.5, 43.8]}, "record_timestamp": "2019-03-10T12:00:00+00:00"}, {"datasetid": "arome-0025-sp1_sp2", "recordid": "arome_0025_sp1_sp2_sp3_lastgrib2-295268", "fields": {"surface_net_thermal_radiation": -13733606.0, "wind_speed": 7.95496073551476, "2_metre_temperature": 6.01667175292971, "dist": "0", "downward_short_wave_radiation_flux": 25172507.125, "surface_net_solar_radiation": 20091274.0625, "timestamp": "2019-03-10T12:00:00+00:00", "surface_latent_heat_flux": -4555328.0, "total_water_precipitation": 0.0, "relative_humidity": 46.27621269226074, "surface_sensible_heat_flux": -4906266.0, "position": [43.8, 4.5], "forecast": "2019-03-12T03:00:00+00:00"}, "geometry": {"type": "Point", "coordinates": [4.5, 43.8]}, "record_timestamp": "2019-03-10T12:00:00+00:00"}, {"datasetid": "arome-0025-sp1_sp2", "recordid": "arome_0025_sp1_sp2_sp3_lastgrib2-7516283", "fields": {"surface_net_thermal_radiation": -13016426.0, "wind_speed": 10.418597012758255, "2_metre_temperature": 7.015557861328148, "dist": "0", "downward_short_wave_radiation_flux": 25172507.125, "surface_net_solar_radiation": 20091274.0625, "timestamp": "2019-03-10T12:00:00+00:00", "surface_latent_heat_flux": -4549440.0, "total_water_precipitation": 0.0, "relative_humidity": 46.183791160583496, "surface_sensible_heat_flux": -5177098.0, "position": [43.8, 4.5], "forecast": "2019-03-12T01:00:00+00:00"}, "geometry": {"type": "Point", "coordinates": [4.5, 43.8]}, "record_timestamp": "2019-03-10T12:00:00+00:00"}, {"datasetid": "arome-0025-sp1_sp2", "recordid": "arome_0025_sp1_sp2_sp3_lastgrib2-1739471", "fields": {"surface_net_thermal_radiation": -8989027.0, "wind_speed": 17.977340679615736, "2_metre_temperature": 14.64887390136721, "dist": "0", "downward_short_wave_radiation_flux": 21362017.625, "surface_net_solar_radiation": 17053992.46875, "timestamp": "2019-03-10T12:00:00+00:00", "surface_latent_heat_flux": -3979092.0, "total_water_precipitation": 0.0, "relative_humidity": 23.87570285797119, "surface_sensible_heat_flux": -4464458.0, "position": [43.8, 4.5], "forecast": "2019-03-11T14:00:00+00:00"}, "geometry": {"type": "Point", "coordinates": [4.5, 43.8]}, "record_timestamp": "2019-03-10T12:00:00+00:00"}, {"datasetid": "arome-0025-sp1_sp2", "recordid": "arome_0025_sp1_sp2_sp3_lastgrib2-12811694", "fields": {"surface_net_thermal_radiation": -3231044.5, "wind_speed": 12.841992728412151, "2_metre_temperature": 12.669030761718773, "dist": "0", "downward_short_wave_radiation_flux": 7215691.8671875, "surface_net_solar_radiation": 5771520.0, "timestamp": "2019-03-10T12:00:00+00:00", "surface_latent_heat_flux": -1465980.0, "total_water_precipitation": 0.0, "relative_humidity": 55.50223159790039, "surface_sensible_heat_flux": -1083848.5, "position": [43.8, 4.5], "forecast": "2019-03-10T23:00:00+00:00"}, "geometry": {"type": "Point", "coordinates": [4.5, 43.8]}, "record_timestamp": "2019-03-10T12:00:00+00:00"}, {"datasetid": "arome-0025-sp1_sp2", "recordid": "arome_0025_sp1_sp2_sp3_lastgrib2-3665075", "fields": {"surface_net_thermal_radiation": -5528669.5, "wind_speed": 10.257867362350225, "2_metre_temperature": 8.66187438964846, "dist": "0", "downward_short_wave_radiation_flux": 7215707.0859375, "surface_net_solar_radiation": 5771520.0, "timestamp": "2019-03-10T12:00:00+00:00", "surface_latent_heat_flux": -1700280.0, "total_water_precipitation": 0.0, "relative_humidity": 47.128929138183594, "surface_sensible_heat_flux": 201102.0, "position": [43.8, 4.5], "forecast": "2019-03-11T06:00:00+00:00"}, "geometry": {"type": "Point", "coordinates": [4.5, 43.8]}, "record_timestamp": "2019-03-10T12:00:00+00:00"}, {"datasetid": "arome-0025-sp1_sp2", "recordid": "arome_0025_sp1_sp2_sp3_lastgrib2-4146476", "fields": {"surface_net_thermal_radiation": -3850447.0, "wind_speed": 12.742365410551429, "2_metre_temperature": 11.05890808105471, "dist": "0", "downward_short_wave_radiation_flux": 7215691.8671875, "surface_net_solar_radiation": 5771520.0, "timestamp": "2019-03-10T12:00:00+00:00", "surface_latent_heat_flux": -1558849.0, "total_water_precipitation": 0.0, "relative_humidity": 51.01361083984375, "surface_sensible_heat_flux": -721098.0, "position": [43.8, 4.5], "forecast": "2019-03-11T01:00:00+00:00"}, "geometry": {"type": "Point", "coordinates": [4.5, 43.8]}, "record_timestamp": "2019-03-10T12:00:00+00:00"}, {"datasetid": "arome-0025-sp1_sp2", "recordid": "arome_0025_sp1_sp2_sp3_lastgrib2-16662902", "fields": {"surface_net_thermal_radiation": -11994108.0, "wind_speed": 8.856301868334413, "2_metre_temperature": 7.702050781250023, "dist": "0", "downward_short_wave_radiation_flux": 25172507.125, "surface_net_solar_radiation": 20091274.0625, "timestamp": "2019-03-10T12:00:00+00:00", "surface_latent_heat_flux": -4542464.0, "total_water_precipitation": 0.0, "relative_humidity": 51.45267391204834, "surface_sensible_heat_flux": -5688920.0, "position": [43.8, 4.5], "forecast": "2019-03-11T22:00:00+00:00"}, "geometry": {"type": "Point", "coordinates": [4.5, 43.8]}, "record_timestamp": "2019-03-10T12:00:00+00:00"}, {"datasetid": "arome-0025-sp1_sp2", "recordid": "arome_0025_sp1_sp2_sp3_lastgrib2-20514110", "fields": {"wind_speed": 4.532863502390683, "2_metre_temperature": 17.361108398437523, "dist": "0", "timestamp": "2019-03-10T12:00:00+00:00", "forecast": "2019-03-10T12:00:00+00:00", "relative_humidity": 58.63327980041504, "position": [43.8, 4.5]}, "geometry": {"type": "Point", "coordinates": [4.5, 43.8]}, "record_timestamp": "2019-03-10T12:00:00+00:00"}, {"datasetid": "arome-0025-sp1_sp2", "recordid": "arome_0025_sp1_sp2_sp3_lastgrib2-19551308", "fields": {"surface_net_thermal_radiation": -14709716.0, "wind_speed": 6.143480027094483, "2_metre_temperature": 4.411645507812523, "dist": "0", "downward_short_wave_radiation_flux": 25172652.375, "surface_net_solar_radiation": 20090796.5, "timestamp": "2019-03-10T12:00:00+00:00", "surface_latent_heat_flux": -4559760.0, "total_water_precipitation": 0.0, "relative_humidity": 55.786590576171875, "surface_sensible_heat_flux": -4678910.0, "position": [43.8, 4.5], "forecast": "2019-03-12T06:00:00+00:00"}, "geometry": {"type": "Point", "coordinates": [4.5, 43.8]}, "record_timestamp": "2019-03-10T12:00:00+00:00"}]}