{"latitude_r":43.8281,"longitude_r":4.5633,"forecast":[{"time":1551582000,"temperature":8.3,"pressure":1020.26,"humidity":61,"wind":5.12,"wind_dir":334.503,"cloud_cover":0},{"time":1551592800,"temperature":6.57,"pressure":1020.18,"humidity":68,"wind":2.77,"wind_dir":332.5,"cloud_cover":0},{"time":1551603600,"temperature":11.96,"pressure":1021.05,"humidity":55,"wind":1.62,"wind_dir":333.501,"cloud_cover":0},{"time":1551614400,"temperature":16.65,"pressure":1020.1,"humidity":55,"wind":1.66,"wind_dir":279.501,"cloud_cover":24},{"time":1551625200,"temperature":17.59,"pressure":1018.24,"humidity":44,"wind":3.1,"wind_dir":230.004,"cloud_cover":24},{"time":1551636000,"temperature":12.61,"pressure":1017.86,"humidity":48,"wind":1.96,"wind_dir":179,"cloud_cover":24},{"time":1551646800,"temperature":8.31,"pressure":1017.52,"humidity":82,"wind":2.17,"wind_dir":114.001,"cloud_cover":56},{"time":1551657600,"temperature":7.06,"pressure":1015.94,"humidity":83,"wind":2.4,"wind_dir":106.5,"cloud_cover":32},{"time":1551668400,"temperature":7.96,"pressure":1012.88,"humidity":82,"wind":4.81,"wind_dir":117.501,"cloud_cover":8},{"time":1551679200,"temperature":10.52,"pressure":1010.93,"humidity":88,"wind":6.16,"wind_dir":139.005,"cloud_cover":12},{"time":1551690000,"temperature":14.05,"pressure":1011.49,"humidity":80,"wind":4.27,"wind_dir":147.502,"cloud_cover":24},{"time":1551700800,"temperature":17.86,"pressure":1011.63,"humidity":60,"precipitation":0.01,"wind":2.66,"wind_dir":300.502,"cloud_cover":56},{"time":1551711600,"temperature":16.56,"pressure":1012.18,"humidity":43,"wind":8.32,"wind_dir":296.002,"cloud_cover":36},{"time":1551722400,"temperature":13.41,"pressure":1014.14,"humidity":40,"wind":7.71,"wind_dir":299,"cloud_cover":0},{"time":1551733200,"temperature":10.99,"pressure":1016.86,"humidity":42,"wind":4.89,"wind_dir":305.5,"cloud_cover":32},{"time":1551744000,"temperature":8.3,"pressure":1017.82,"humidity":50,"wind":3.11,"wind_dir":283.001,"cloud_cover":12},{"time":1551754800,"temperature":6.28,"pressure":1017.58,"humidity":66,"wind":2.57,"wind_dir":272.5,"cloud_cover":8},{"time":1551765600,"temperature":4.04,"pressure":1017.36,"humidity":87,"wind":2.17,"wind_dir":237.507,"cloud_cover":0},{"time":1551776400,"temperature":11.27,"pressure":1017.62,"humidity":60,"wind":1.61,"wind_dir":246.002,"cloud_cover":8},{"time":1551787200,"temperature":15.64,"pressure":1016.7,"humidity":56,"wind":1.97,"wind_dir":215,"cloud_cover":12},{"time":1551798000,"temperature":15.65,"pressure":1014.75,"humidity":48,"wind":4.46,"wind_dir":200.501,"cloud_cover":48},{"time":1551808800,"temperature":12.01,"pressure":1014.11,"humidity":54,"wind":2.87,"wind_dir":160.502,"cloud_cover":0},{"time":1551819600,"temperature":8.4,"pressure":1014.4,"humidity":81,"wind":3.16,"wind_dir":125.003,"cloud_cover":0},{"time":1551830400,"temperature":7.82,"pressure":1013.62,"humidity":80,"wind":3.46,"wind_dir":99.0005,"cloud_cover":20},{"time":1551841200,"temperature":7.61,"pressure":1012.11,"humidity":76,"wind":3.81,"wind_dir":100.5,"cloud_cover":8},{"time":1551852000,"temperature":8.64,"pressure":1011.04,"humidity":85,"wind":5.01,"wind_dir":116,"cloud_cover":56},{"time":1551862800,"temperature":12.63,"pressure":1010.94,"humidity":79,"precipitation":0.1,"wind":6.53,"wind_dir":125.5,"cloud_cover":92},{"time":1551873600,"temperature":16.24,"pressure":1009.93,"humidity":65,"precipitation":0.03,"wind":8.41,"wind_dir":151.503,"cloud_cover":64},{"time":1551884400,"temperature":18.07,"pressure":1008.92,"humidity":54,"wind":7.52,"wind_dir":175,"cloud_cover":20},{"time":1551895200,"temperature":15.53,"pressure":1008.89,"humidity":63,"wind":6.42,"wind_dir":164.002,"cloud_cover":44},{"time":1551906000,"temperature":13.92,"pressure":1008.89,"humidity":72,"wind":6.72,"wind_dir":146.502,"cloud_cover":36},{"time":1551916800,"temperature":13.62,"pressure":1008.36,"humidity":70,"wind":5.74,"wind_dir":152.5,"cloud_cover":36},{"time":1551927600,"temperature":12.35,"pressure":1007.7,"humidity":80,"wind":4.62,"wind_dir":140.004,"cloud_cover":12},{"time":1551938400,"temperature":11.13,"pressure":1007.86,"humidity":90,"wind":4.01,"wind_dir":135.501,"cloud_cover":20},{"time":1551949200,"temperature":15.44,"pressure":1009.4,"humidity":73,"wind":1.77,"wind_dir":120.003,"cloud_cover":32},{"time":1551960000,"temperature":18.81,"pressure":1009.56,"humidity":68,"wind":2.06,"wind_dir":306.003,"cloud_cover":32},{"time":1551970800,"temperature":18.38,"pressure":1008.73,"humidity":56,"wind":3.16,"wind_dir":324.002,"cloud_cover":64},{"time":1551981600,"temperature":15.1,"pressure":1009.09,"humidity":56,"wind":2.57,"wind_dir":350.005,"cloud_cover":24},{"time":1551992400,"temperature":10.97,"pressure":1010.05,"humidity":73,"wind":1.66,"wind_dir":345.506,"cloud_cover":68}],"source":"open_weather_map","longitude_q":4.5839,"latitude_q":43.8344,"time_q":1551571231,"time_r":null}