{"latitude":43.7137,"longitude":4.4083,"timezone":"Europe/Paris","currently":{"time":1552197606,"summary":"Faibles Passages Nuageux","icon":"partly-cloudy-night","precipIntensity":0,"precipProbability":0,"temperature":10.84,"apparentTemperature":10.84,"dewPoint":7.84,"humidity":0.82,"pressure":1024.95,"windSpeed":1.05,"windGust":2.6,"windBearing":163,"cloudCover":0.4,"uvIndex":0,"visibility":9.83,"ozone":272.12},"hourly":{"summary":"Ciel nuageux toute la journée.","icon":"partly-cloudy-night","data":[{"time":1552197600,"summary":"Faibles Passages Nuageux","icon":"partly-cloudy-night","precipIntensity":0,"precipProbability":0,"temperature":10.84,"apparentTemperature":10.84,"dewPoint":7.84,"humidity":0.82,"pressure":1024.95,"windSpeed":1.05,"windGust":2.6,"windBearing":162,"cloudCover":0.4,"uvIndex":0,"visibility":9.82,"ozone":272.12},{"time":1552201200,"summary":"Faibles Passages Nuageux","icon":"partly-cloudy-day","precipIntensity":0,"precipProbability":0,"temperature":12.33,"apparentTemperature":12.33,"dewPoint":8.27,"humidity":0.76,"pressure":1025.12,"windSpeed":1.39,"windGust":2.81,"windBearing":170,"cloudCover":0.37,"uvIndex":0,"visibility":11.44,"ozone":273.08},{"time":1552204800,"summary":"Faibles Passages Nuageux","icon":"partly-cloudy-day","precipIntensity":0,"precipProbability":0,"temperature":14.36,"apparentTemperature":14.36,"dewPoint":9.18,"humidity":0.71,"pressure":1025.37,"windSpeed":1.72,"windGust":3.55,"windBearing":281,"cloudCover":0.34,"uvIndex":1,"visibility":16.09,"ozone":274.22},{"time":1552208400,"summary":"Faibles Passages Nuageux","icon":"partly-cloudy-day","precipIntensity":0,"precipProbability":0,"temperature":16.24,"apparentTemperature":16.24,"dewPoint":9.73,"humidity":0.65,"pressure":1025.49,"windSpeed":3.59,"windGust":4.89,"windBearing":262,"cloudCover":0.34,"uvIndex":2,"visibility":16.09,"ozone":275.13},{"time":1552212000,"summary":"Faibles Passages Nuageux","icon":"partly-cloudy-day","precipIntensity":0,"precipProbability":0,"temperature":17.89,"apparentTemperature":17.89,"dewPoint":9.61,"humidity":0.58,"pressure":1025.4,"windSpeed":4.46,"windGust":7.36,"windBearing":225,"cloudCover":0.38,"uvIndex":3,"visibility":16.09,"ozone":275.57},{"time":1552215600,"summary":"Faibles Passages Nuageux","icon":"partly-cloudy-day","precipIntensity":0,"precipProbability":0,"temperature":19.29,"apparentTemperature":19.29,"dewPoint":9.2,"humidity":0.52,"pressure":1025.16,"windSpeed":5.98,"windGust":10.44,"windBearing":321,"cloudCover":0.44,"uvIndex":4,"visibility":16.09,"ozone":275.73},{"time":1552219200,"summary":"Faibles Passages Nuageux","icon":"partly-cloudy-day","precipIntensity":0,"precipProbability":0,"temperature":19.73,"apparentTemperature":19.73,"dewPoint":8.77,"humidity":0.49,"pressure":1024.85,"windSpeed":7.33,"windGust":12.69,"windBearing":292,"cloudCover":0.54,"uvIndex":4,"visibility":16.09,"ozone":275.73},{"time":1552222800,"summary":"Ciel Nuageux","icon":"partly-cloudy-day","precipIntensity":0,"precipProbability":0,"temperature":19.85,"apparentTemperature":19.85,"dewPoint":8.35,"humidity":0.47,"pressure":1024.44,"windSpeed":7.14,"windGust":13.46,"windBearing":282,"cloudCover":0.68,"uvIndex":4,"visibility":16.09,"ozone":275.18},{"time":1552226400,"summary":"Ciel Nuageux","icon":"partly-cloudy-day","precipIntensity":0,"precipProbability":0,"temperature":19.61,"apparentTemperature":19.61,"dewPoint":7.91,"humidity":0.47,"pressure":1023.95,"windSpeed":7.34,"windGust":13.43,"windBearing":303,"cloudCover":0.86,"uvIndex":3,"visibility":16.09,"ozone":274.29},{"time":1552230000,"summary":"Ciel Couvert","icon":"cloudy","precipIntensity":0,"precipProbability":0,"temperature":19.4,"apparentTemperature":19.4,"dewPoint":7.5,"humidity":0.46,"pressure":1023.62,"windSpeed":7.69,"windGust":13.17,"windBearing":301,"cloudCover":0.98,"uvIndex":2,"visibility":16.09,"ozone":274.18},{"time":1552233600,"summary":"Ciel Couvert","icon":"cloudy","precipIntensity":0,"precipProbability":0,"temperature":18.74,"apparentTemperature":18.74,"dewPoint":7.21,"humidity":0.47,"pressure":1023.52,"windSpeed":7.34,"windGust":12.78,"windBearing":298,"cloudCover":1,"uvIndex":1,"visibility":16.09,"ozone":274.88},{"time":1552237200,"summary":"Ciel Couvert","icon":"cloudy","precipIntensity":0,"precipProbability":0,"temperature":17.91,"apparentTemperature":17.91,"dewPoint":6.94,"humidity":0.49,"pressure":1023.61,"windSpeed":6.89,"windGust":12.18,"windBearing":298,"cloudCover":1,"uvIndex":0,"visibility":16.09,"ozone":276.2},{"time":1552240800,"summary":"Ciel Couvert","icon":"cloudy","precipIntensity":0,"precipProbability":0,"temperature":16.98,"apparentTemperature":16.98,"dewPoint":6.51,"humidity":0.5,"pressure":1023.85,"windSpeed":6.52,"windGust":11.66,"windBearing":299,"cloudCover":0.99,"uvIndex":0,"visibility":16.09,"ozone":278.98},{"time":1552244400,"summary":"Ciel Couvert","icon":"cloudy","precipIntensity":0,"precipProbability":0,"temperature":16.12,"apparentTemperature":16.12,"dewPoint":5.85,"humidity":0.51,"pressure":1024.36,"windSpeed":6.33,"windGust":11.27,"windBearing":301,"cloudCover":0.98,"uvIndex":0,"visibility":16.09,"ozone":284.14},{"time":1552248000,"summary":"Ciel Couvert","icon":"cloudy","precipIntensity":0,"precipProbability":0,"temperature":15.25,"apparentTemperature":15.25,"dewPoint":5.08,"humidity":0.51,"pressure":1025.06,"windSpeed":6.22,"windGust":10.97,"windBearing":304,"cloudCover":0.96,"uvIndex":0,"visibility":16.09,"ozone":290.87},{"time":1552251600,"summary":"Ciel Couvert","icon":"cloudy","precipIntensity":0,"precipProbability":0,"temperature":14.37,"apparentTemperature":14.37,"dewPoint":4.31,"humidity":0.51,"pressure":1025.67,"windSpeed":6.2,"windGust":10.91,"windBearing":307,"cloudCover":0.94,"uvIndex":0,"visibility":16.09,"ozone":297.06},{"time":1552255200,"summary":"Ciel Nuageux","icon":"partly-cloudy-night","precipIntensity":0,"precipProbability":0,"temperature":13.54,"apparentTemperature":13.54,"dewPoint":3.48,"humidity":0.51,"pressure":1026.1,"windSpeed":6.31,"windGust":11.22,"windBearing":311,"cloudCover":0.92,"uvIndex":0,"visibility":16.09,"ozone":301.85},{"time":1552258800,"summary":"Ciel Nuageux","icon":"partly-cloudy-night","precipIntensity":0,"precipProbability":0,"temperature":12.74,"apparentTemperature":12.74,"dewPoint":2.64,"humidity":0.5,"pressure":1026.45,"windSpeed":6.47,"windGust":11.75,"windBearing":316,"cloudCover":0.89,"uvIndex":0,"visibility":16.09,"ozone":306.3},{"time":1552262400,"summary":"Ciel Nuageux","icon":"partly-cloudy-night","precipIntensity":0,"precipProbability":0,"temperature":12.04,"apparentTemperature":12.04,"dewPoint":1.94,"humidity":0.5,"pressure":1026.71,"windSpeed":6.58,"windGust":12.16,"windBearing":320,"cloudCover":0.86,"uvIndex":0,"visibility":16.09,"ozone":311.49},{"time":1552266000,"summary":"Ciel Nuageux","icon":"partly-cloudy-night","precipIntensity":0,"precipProbability":0,"temperature":11.48,"apparentTemperature":11.48,"dewPoint":1.41,"humidity":0.5,"pressure":1026.9,"windSpeed":6.57,"windGust":12.23,"windBearing":321,"cloudCover":0.84,"uvIndex":0,"visibility":16.09,"ozone":318.7},{"time":1552269600,"summary":"Ciel Nuageux","icon":"partly-cloudy-night","precipIntensity":0,"precipProbability":0,"temperature":10.94,"apparentTemperature":10.94,"dewPoint":1.01,"humidity":0.5,"pressure":1027.05,"windSpeed":6.54,"windGust":12.16,"windBearing":319,"cloudCover":0.81,"uvIndex":0,"visibility":16.09,"ozone":326.78},{"time":1552273200,"summary":"Ciel Nuageux","icon":"partly-cloudy-night","precipIntensity":0,"precipProbability":0,"temperature":10.37,"apparentTemperature":10.37,"dewPoint":0.66,"humidity":0.51,"pressure":1027.27,"windSpeed":6.49,"windGust":12.16,"windBearing":320,"cloudCover":0.76,"uvIndex":0,"visibility":16.09,"ozone":333.52},{"time":1552276800,"summary":"Ciel Nuageux","icon":"partly-cloudy-night","precipIntensity":0,"precipProbability":0,"temperature":9.55,"apparentTemperature":6.56,"dewPoint":0.34,"humidity":0.53,"pressure":1027.62,"windSpeed":6.36,"windGust":12.3,"windBearing":324,"cloudCover":0.65,"uvIndex":0,"visibility":16.09,"ozone":338.25},{"time":1552280400,"summary":"Faibles Passages Nuageux","icon":"partly-cloudy-night","precipIntensity":0,"precipProbability":0,"temperature":8.88,"apparentTemperature":5.74,"dewPoint":0.06,"humidity":0.54,"pressure":1028.03,"windSpeed":6.22,"windGust":12.49,"windBearing":328,"cloudCover":0.53,"uvIndex":0,"visibility":16.09,"ozone":341.67},{"time":1552284000,"summary":"Faibles Passages Nuageux","icon":"partly-cloudy-night","precipIntensity":0,"precipProbability":0,"temperature":8.63,"apparentTemperature":5.43,"dewPoint":-0.09,"humidity":0.54,"pressure":1028.45,"windSpeed":6.21,"windGust":12.74,"windBearing":332,"cloudCover":0.39,"uvIndex":0,"visibility":16.09,"ozone":343.5},{"time":1552287600,"summary":"Faibles Passages Nuageux","icon":"partly-cloudy-day","precipIntensity":0,"precipProbability":0,"temperature":9.32,"apparentTemperature":6.22,"dewPoint":-0.03,"humidity":0.52,"pressure":1028.91,"windSpeed":6.46,"windGust":13.14,"windBearing":332,"cloudCover":0.25,"uvIndex":0,"visibility":16.09,"ozone":342.88},{"time":1552291200,"summary":"Ciel Dégagé","icon":"clear-day","precipIntensity":0,"precipProbability":0,"temperature":10.31,"apparentTemperature":10.31,"dewPoint":0.09,"humidity":0.49,"pressure":1029.35,"windSpeed":6.91,"windGust":13.59,"windBearing":332,"cloudCover":0.1,"uvIndex":1,"visibility":16.09,"ozone":340.67},{"time":1552294800,"summary":"Ciel Dégagé","icon":"clear-day","precipIntensity":0,"precipProbability":0,"temperature":11.16,"apparentTemperature":11.16,"dewPoint":0.07,"humidity":0.46,"pressure":1029.57,"windSpeed":7.36,"windGust":13.8,"windBearing":331,"cloudCover":0,"uvIndex":2,"visibility":16.09,"ozone":338.99},{"time":1552298400,"summary":"Ciel Dégagé","icon":"clear-day","precipIntensity":0,"precipProbability":0,"temperature":12.32,"apparentTemperature":12.32,"dewPoint":-0.03,"humidity":0.43,"pressure":1029.44,"windSpeed":7.63,"windGust":13.53,"windBearing":332,"cloudCover":0,"uvIndex":3,"visibility":16.09,"ozone":338.83},{"time":1552302000,"summary":"Ciel Dégagé","icon":"clear-day","precipIntensity":0,"precipProbability":0,"temperature":13.46,"apparentTemperature":13.46,"dewPoint":-0.14,"humidity":0.39,"pressure":1029.1,"windSpeed":7.78,"windGust":13.03,"windBearing":334,"cloudCover":0,"uvIndex":4,"visibility":16.09,"ozone":339.23},{"time":1552305600,"summary":"Ciel Dégagé","icon":"clear-day","precipIntensity":0,"precipProbability":0,"temperature":14.57,"apparentTemperature":14.57,"dewPoint":-0.34,"humidity":0.36,"pressure":1028.71,"windSpeed":7.93,"windGust":12.61,"windBearing":336,"cloudCover":0,"uvIndex":4,"visibility":16.09,"ozone":338.92},{"time":1552309200,"summary":"Ciel Dégagé","icon":"clear-day","precipIntensity":0,"precipProbability":0,"temperature":15.41,"apparentTemperature":15.41,"dewPoint":-0.64,"humidity":0.33,"pressure":1028.2,"windSpeed":8.35,"windGust":12.48,"windBearing":338,"cloudCover":0,"uvIndex":4,"visibility":16.09,"ozone":337.26},{"time":1552312800,"summary":"Vent Faible","icon":"wind","precipIntensity":0,"precipProbability":0,"temperature":16.01,"apparentTemperature":16.01,"dewPoint":-1.04,"humidity":0.31,"pressure":1027.67,"windSpeed":8.81,"windGust":12.44,"windBearing":341,"cloudCover":0,"uvIndex":3,"visibility":16.09,"ozone":334.95},{"time":1552316400,"summary":"Vent Faible","icon":"wind","precipIntensity":0,"precipProbability":0,"temperature":16.09,"apparentTemperature":16.09,"dewPoint":-1.41,"humidity":0.3,"pressure":1027.41,"windSpeed":8.84,"windGust":12.29,"windBearing":344,"cloudCover":0,"uvIndex":2,"visibility":16.09,"ozone":332.76},{"time":1552320000,"summary":"Ciel Dégagé","icon":"clear-day","precipIntensity":0,"precipProbability":0,"temperature":15.35,"apparentTemperature":15.35,"dewPoint":-1.69,"humidity":0.31,"pressure":1027.74,"windSpeed":8.08,"windGust":11.87,"windBearing":346,"cloudCover":0,"uvIndex":1,"visibility":16.09,"ozone":331.23},{"time":1552323600,"summary":"Ciel Dégagé","icon":"clear-day","precipIntensity":0,"precipProbability":0,"temperature":13.97,"apparentTemperature":13.97,"dewPoint":-1.97,"humidity":0.33,"pressure":1028.34,"windSpeed":6.91,"windGust":11.33,"windBearing":350,"cloudCover":0,"uvIndex":0,"visibility":16.09,"ozone":329.96},{"time":1552327200,"summary":"Ciel Dégagé","icon":"clear-night","precipIntensity":0,"precipProbability":0,"temperature":12.74,"apparentTemperature":12.74,"dewPoint":-2.22,"humidity":0.35,"pressure":1029.05,"windSpeed":5.94,"windGust":10.95,"windBearing":352,"cloudCover":0,"uvIndex":0,"visibility":16.09,"ozone":328.58},{"time":1552330800,"summary":"Ciel Dégagé","icon":"clear-night","precipIntensity":0,"precipProbability":0,"temperature":11.63,"apparentTemperature":11.63,"dewPoint":-2.5,"humidity":0.37,"pressure":1029.8,"windSpeed":5.42,"windGust":10.85,"windBearing":353,"cloudCover":0,"uvIndex":0,"visibility":16.09,"ozone":327.12},{"time":1552334400,"summary":"Ciel Dégagé","icon":"clear-night","precipIntensity":0,"precipProbability":0,"temperature":10.66,"apparentTemperature":10.66,"dewPoint":-2.72,"humidity":0.39,"pressure":1030.6,"windSpeed":5.09,"windGust":10.89,"windBearing":351,"cloudCover":0,"uvIndex":0,"visibility":16.09,"ozone":325.44},{"time":1552338000,"summary":"Ciel Dégagé","icon":"clear-night","precipIntensity":0.0051,"precipProbability":0.01,"precipType":"rain","temperature":9.82,"apparentTemperature":7.43,"dewPoint":-2.81,"humidity":0.41,"pressure":1031.16,"windSpeed":4.83,"windGust":11.06,"windBearing":350,"cloudCover":0,"uvIndex":0,"visibility":16.09,"ozone":323.4},{"time":1552341600,"summary":"Ciel Dégagé","icon":"clear-night","precipIntensity":0,"precipProbability":0,"temperature":9.02,"apparentTemperature":6.49,"dewPoint":-2.72,"humidity":0.44,"pressure":1031.28,"windSpeed":4.7,"windGust":11.49,"windBearing":351,"cloudCover":0,"uvIndex":0,"visibility":16.09,"ozone":321.28},{"time":1552345200,"summary":"Ciel Dégagé","icon":"clear-night","precipIntensity":0,"precipProbability":0,"temperature":8.37,"apparentTemperature":5.7,"dewPoint":-2.49,"humidity":0.46,"pressure":1031.12,"windSpeed":4.65,"windGust":12.04,"windBearing":352,"cloudCover":0,"uvIndex":0,"visibility":16.09,"ozone":318.6},{"time":1552348800,"summary":"Ciel Dégagé","icon":"clear-night","precipIntensity":0,"precipProbability":0,"temperature":7.77,"apparentTemperature":4.99,"dewPoint":-2.26,"humidity":0.49,"pressure":1030.87,"windSpeed":4.56,"windGust":12.25,"windBearing":354,"cloudCover":0,"uvIndex":0,"visibility":16.09,"ozone":313.77},{"time":1552352400,"summary":"Ciel Dégagé","icon":"clear-night","precipIntensity":0,"precipProbability":0,"temperature":7.09,"apparentTemperature":4.23,"dewPoint":-2.05,"humidity":0.52,"pressure":1030.47,"windSpeed":4.39,"windGust":12.01,"windBearing":357,"cloudCover":0,"uvIndex":0,"visibility":16.09,"ozone":304.54},{"time":1552356000,"summary":"Ciel Dégagé","icon":"clear-night","precipIntensity":0,"precipProbability":0,"temperature":6.5,"apparentTemperature":3.61,"dewPoint":-1.84,"humidity":0.55,"pressure":1029.95,"windSpeed":4.18,"windGust":11.41,"windBearing":359,"cloudCover":0,"uvIndex":0,"visibility":16.09,"ozone":293.16},{"time":1552359600,"summary":"Ciel Dégagé","icon":"clear-night","precipIntensity":0,"precipProbability":0,"temperature":5.93,"apparentTemperature":3.06,"dewPoint":-1.71,"humidity":0.58,"pressure":1029.45,"windSpeed":3.9,"windGust":10.33,"windBearing":357,"cloudCover":0,"uvIndex":0,"visibility":16.09,"ozone":284.06},{"time":1552363200,"summary":"Ciel Dégagé","icon":"clear-night","precipIntensity":0,"precipProbability":0,"temperature":5.03,"apparentTemperature":2.18,"dewPoint":-1.64,"humidity":0.62,"pressure":1028.99,"windSpeed":3.54,"windGust":8.4,"windBearing":348,"cloudCover":0,"uvIndex":0,"visibility":16.09,"ozone":279.44},{"time":1552366800,"summary":"Ciel Dégagé","icon":"clear-night","precipIntensity":0,"precipProbability":0,"temperature":4.09,"apparentTemperature":1.33,"dewPoint":-1.65,"humidity":0.66,"pressure":1028.55,"windSpeed":3.11,"windGust":5.98,"windBearing":333,"cloudCover":0.01,"uvIndex":0,"visibility":16.09,"ozone":277.09},{"time":1552370400,"summary":"Ciel Dégagé","icon":"clear-night","precipIntensity":0,"precipProbability":0,"temperature":4.16,"apparentTemperature":1.72,"dewPoint":-1.65,"humidity":0.66,"pressure":1028.13,"windSpeed":2.72,"windGust":4.01,"windBearing":325,"cloudCover":0.01,"uvIndex":0,"visibility":16.09,"ozone":275.46}]},"offset":1}