{"latitude_r":43.72,"longitude_r":4.33,"time_r":1.55101811E9,"latitude_q":43.7137,"longitude_q":4.4083,"time_q":1551031202,"source":"meteo_concept","forecast":[{"time":1551031200,"temperature":10.0,"precipitation":0.0,"wind":2.5,"wind_dir":236.0,"humidity":75.0,"pressure":null,"cloud_cover":null},{"time":1551034800,"temperature":10.0,"precipitation":0.0,"wind":2.2222223,"wind_dir":246.0,"humidity":77.0,"pressure":null,"cloud_cover":null},{"time":1551038400,"temperature":9.0,"precipitation":0.0,"wind":2.2222223,"wind_dir":253.0,"humidity":78.0,"pressure":null,"cloud_cover":null},{"time":1551042000,"temperature":9.0,"precipitation":0.0,"wind":2.2222223,"wind_dir":259.0,"humidity":79.0,"pressure":null,"cloud_cover":null},{"time":1551045600,"temperature":8.0,"precipitation":0.0,"wind":1.9444444,"wind_dir":260.0,"humidity":79.0,"pressure":null,"cloud_cover":null},{"time":1551049200,"temperature":8.0,"precipitation":0.0,"wind":1.6666666,"wind_dir":263.0,"humidity":81.0,"pressure":null,"cloud_cover":null},{"time":1551052800,"temperature":7.0,"precipitation":0.0,"wind":1.9444444,"wind_dir":273.0,"humidity":80.0,"pressure":null,"cloud_cover":null},{"time":1551056400,"temperature":7.0,"precipitation":0.0,"wind":2.2222223,"wind_dir":325.0,"humidity":80.0,"pressure":null,"cloud_cover":null},{"time":1551060000,"temperature":7.0,"precipitation":0.0,"wind":1.9444444,"wind_dir":32.0,"humidity":80.0,"pressure":null,"cloud_cover":null},{"time":1551063600,"temperature":7.0,"precipitation":0.0,"wind":2.5,"wind_dir":55.0,"humidity":80.0,"pressure":null,"cloud_cover":null},{"time":1551067200,"temperature":7.0,"precipitation":0.0,"wind":2.2222223,"wind_dir":69.0,"humidity":81.0,"pressure":null,"cloud_cover":null},{"time":1551070800,"temperature":6.0,"precipitation":0.0,"wind":2.5,"wind_dir":83.0,"humidity":87.0,"pressure":null,"cloud_cover":null},{"time":1551074400,"temperature":5.0,"precipitation":0.0,"wind":1.9444444,"wind_dir":81.0,"humidity":90.0,"pressure":null,"cloud_cover":null}]}